anyeval/__init__.py
anyeval/packer.py
anyeval/backend/__about__.py
anyeval/backend/__init__.py
anyeval/backend/app.py
anyeval/backend/proxy.py
anyeval/backend/static/asset-manifest.json
anyeval/backend/static/favicon.ico
anyeval/backend/static/index.html
anyeval/backend/static/manifest.json
anyeval/backend/static/static/js/main.0a19bbce.js
anyeval/backend/static/static/js/main.0a19bbce.js.LICENSE.txt
anyeval/backend/static/static/js/main.0a19bbce.js.map
anyeval/cli/__init__.py
anyeval/cli/main.py
anyeval-0.1.6.dist-info/licenses/LICENSE
anyeval-0.1.6.dist-info/METADATA
anyeval-0.1.6.dist-info/WHEEL
anyeval-0.1.6.dist-info/entry_points.txt
anyeval-0.1.6.dist-info/top_level.txt
anyeval-0.1.6.dist-info/RECORD
