Metadata-Version: 2.4
Name: anyeval
Version: 0.1.6
Summary: Universal Evaluation for Gen AI
License:                                  Apache License
Requires-Python: >=3.10
License-File: LICENSE
Requires-Dist: fastapi>=0.104.0
Requires-Dist: uvicorn>=0.23.2
Requires-Dist: pydantic>=2.4.2
Requires-Dist: typer>=0.9.0
Requires-Dist: pandas>=2.0.0
Requires-Dist: pyarrow>=14.0.0
Requires-Dist: opendal>=0.45.19
Requires-Dist: duckdb>=1.2.0
Dynamic: license-file
